{"name":"Retour de voiture","testSteps":[{"number":1,"description":"ca.uqam.acceptancetests.steps.AfficherclientStep.setUp()","duration":59,"startTime":1480289533420,"exception":{"errorType":"org.jbehave.core.failures.BeforeOrAfterFailed","message":"Method setUp (annotated with @BeforeScenario in class ca.uqam.acceptancetests.steps.AfficherclientStep) failed: org.springframework.beans.factory.BeanCreationException: Error creating bean with name \u0027locationsRepository\u0027: Invocation of init method failed; nested exception is java.lang.IllegalArgumentException: Could not create query metamodel for method public abstract java.util.List ca.uqam.repositories.LocationsRepository.findByClientID(java.lang.Long)!","stackTrace":[]},"result":"ERROR"},{"number":2,"description":"Given la voiture A1 est louée à Paul","duration":1,"startTime":1480289533517,"result":"SKIPPED"},{"number":3,"description":"When Paul retourne la voiture A1","duration":1,"startTime":1480289533648,"result":"SKIPPED"},{"number":4,"description":"Then A1 est disponible","duration":0,"startTime":1480289533650,"result":"SKIPPED"},{"number":5,"description":"ca.uqam.acceptancetests.steps.AfficherclientStep.tearDown()","duration":2,"startTime":1480289533785,"exception":{"errorType":"org.jbehave.core.failures.BeforeOrAfterFailed","message":"Method tearDown (annotated with @AfterScenario in class ca.uqam.acceptancetests.steps.AfficherclientStep) failed: java.lang.NullPointerException","stackTrace":[]},"result":"ERROR"}],"userStory":{"id":"Retour_Voiture","storyName":"Retour  voiture","path":"stories/Retour_Voiture.story","narrative":"As a user\nI want to return a car\nSo that I can change the car status to available","type":"story"},"title":"Retour de voiture","tags":[{"name":"Retour  voiture","type":"story"},{"name":"Retour voiture","type":"story"}],"startTime":1480289522378,"duration":11431,"testFailureCause":{"errorType":"java.lang.NullPointerException","stackTrace":[{"declaringClass":"ca.uqam.acceptancetests.steps.AfficherclientStep","methodName":"tearDown","fileName":"AfficherclientStep.java","lineNumber":29}]},"testFailureClassname":"java.lang.NullPointerException","annotatedResult":"ERROR","manual":false,"result":"ERROR"}